{
  "users": [
    {
      "name": "Jane Doe",
      "email": "jane@gmail.com",
      "contactNumber": "7785432512",
      "address": "San Diego",
      "dateOfBirth": "1995-03-04",
      "ssn": "123498765",
      "accountType": "savings",
      "password": "jane@123",
      "id": 8
    },
    {
      "name": "Sarah",
      "email": "sarah123@gmail.com",
      "contactNumber": "7788554433",
      "address": "Bangalore",
      "dateOfBirth": "1997-07-08",
      "ssn": " 987-65-4321",
      "accountType": "checking",
      "password": "sarah@123",
      "id": 9
    }
  ]
}